yaml2resume/__init__.py
yaml2resume/cli.py
yaml2resume/helpers.py
yaml2resume/output.py
yaml2resume/parse.py
yaml2resume/skel/README.md
yaml2resume/skel/base.yaml
yaml2resume/skel/config.yaml
yaml2resume/skel/technical.yaml
yaml2resume/skel/static/.placeholder
yaml2resume/skel/templates/html.j2
yaml2resume/skel/templates/txt.j2
yaml2resume-0.0.11.dist-info/LICENSE
yaml2resume-0.0.11.dist-info/METADATA
yaml2resume-0.0.11.dist-info/WHEEL
yaml2resume-0.0.11.dist-info/entry_points.txt
yaml2resume-0.0.11.dist-info/top_level.txt
yaml2resume-0.0.11.dist-info/RECORD
