Metadata-Version: 2.1
Name: yaml2resume
Version: 0.0.11
Summary: Take yaml files and convert them into a resume
Home-page: https://github.com/jpleger/yaml2resume
Author: James Pleger
Author-email: jpleger@gmail.com
License: UNKNOWN
Project-URL: Bug Tracker, https://github.com/jpleger/yaml2resume/issues
Platform: UNKNOWN
Classifier: Programming Language :: Python :: 3
Classifier: License :: OSI Approved :: MIT License
Classifier: Operating System :: OS Independent
Requires-Python: >=3.6
Requires-Dist: Jinja2 (>=2.11.3)
Requires-Dist: PyYAML (>=5.4.1)
Requires-Dist: pyspellchecker (>=0.6.2)
